StaticScrape/__init__.py
StaticScrape/front_clone.py
staticscrape-0.2.1.dist-info/LICENSE
staticscrape-0.2.1.dist-info/METADATA
staticscrape-0.2.1.dist-info/WHEEL
staticscrape-0.2.1.dist-info/entry_points.txt
staticscrape-0.2.1.dist-info/top_level.txt
staticscrape-0.2.1.dist-info/RECORD
