Metadata-Version: 2.2
Name: StaticScrape
Version: 0.2.1
Summary: A command-line tool to clone any website's front end
Author: Anurag Singh Bhandari
Author-email: anuoo3ups@gmail.com
License: MIT
Classifier: License :: OSI Approved :: MIT License
Classifier: Programming Language :: Python :: 3
Classifier: Operating System :: OS Independent
Requires-Python: >=3.6
License-File: LICENSE
Requires-Dist: playwright
Requires-Dist: beautifulsoup4
Requires-Dist: lxml
Dynamic: author
Dynamic: author-email
Dynamic: classifier
Dynamic: description
Dynamic: description-content-type
Dynamic: license
Dynamic: requires-dist
Dynamic: requires-python
Dynamic: summary
